[{"game":"Card 1","wins":8,"duplicates":1},{"game":"Card 2","wins":4,"duplicates":2},{"game":"Card 3","wins":10,"duplicates":4},{"game":"Card 4","wins":10,"duplicates":8},{"game":"Card 5","wins":4,"duplicates":16},{"game":"Card 6","wins":6,"duplicates":32},{"game":"Card 7","wins":10,"duplicates":62},{"game":"Card 8","wins":4,"duplicates":124},{"game":"Card 9","wins":10,"duplicates":248},{"game":"Card 10","wins":0,"duplicates":479},{"game":"Card 11","wins":0,"duplicates":479},{"game":"Card 12","wins":3,"duplicates":479},{"game":"Card 13","wins":7,"duplicates":802},{"game":"Card 14","wins":5,"duplicates":1600},{"game":"Card 15","wins":7,"duplicates":3192},{"game":"Card 16","wins":8,"duplicates":5905},{"game":"Card 17","wins":1,"duplicates":11810},{"game":"Card 18","wins":5,"duplicates":23558},{"game":"Card 19","wins":0,"duplicates":35306},{"game":"Card 20","wins":0,"duplicates":33458},{"game":"Card 21","wins":2,"duplicates":32656},{"game":"Card 22","wins":2,"duplicates":65312},{"game":"Card 23","wins":1,"duplicates":127432},{"game":"Card 24","wins":0,"duplicates":198650},{"game":"Card 25","wins":8,"duplicates":1},{"game":"Card 26","wins":7,"duplicates":2},{"game":"Card 27","wins":10,"duplicates":4},{"game":"Card 28","wins":7,"duplicates":8},{"game":"Card 29","wins":1,"duplicates":16},{"game":"Card 30","wins":10,"duplicates":32},{"game":"Card 31","wins":8,"duplicates":48},{"game":"Card 32","wins":10,"duplicates":96},{"game":"Card 33","wins":10,"duplicates":192},{"game":"Card 34","wins":10,"duplicates":381},{"game":"Card 35","wins":0,"duplicates":762},{"game":"Card 36","wins":9,"duplicates":754},{"game":"Card 37","wins":6,"duplicates":1508},{"game":"Card 38","wins":1,"duplicates":3012},{"game":"Card 39","wins":5,"duplicates":6024},{"game":"Card 40","wins":2,"duplicates":8988},{"game":"Card 41","wins":4,"duplicates":17944},{"game":"Card 42","wins":7,"duplicates":35888},{"game":"Card 43","wins":4,"duplicates":62692},{"game":"Card 44","wins":1,"duplicates":123684},{"game":"Card 45","wins":4,"duplicates":240963},{"game":"Card 46","wins":3,"duplicates":339544},{"game":"Card 47","wins":1,"duplicates":679088},{"game":"Card 48","wins":1,"duplicates":1295484},{"game":"Card 49","wins":0,"duplicates":1911880},{"game":"Card 50","wins":6,"duplicates":1},{"game":"Card 51","wins":10,"duplicates":2},{"game":"Card 52","wins":10,"duplicates":4},{"game":"Card 53","wins":10,"duplicates":8},{"game":"Card 54","wins":0,"duplicates":16},{"game":"Card 55","wins":10,"duplicates":16},{"game":"Card 56","wins":4,"duplicates":32},{"game":"Card 57","wins":1,"duplicates":63},{"game":"Card 58","wins":8,"duplicates":126},{"game":"Card 59","wins":1,"duplicates":189},{"game":"Card 60","wins":2,"duplicates":378},{"game":"Card 61","wins":1,"duplicates":535},{"game":"Card 62","wins":3,"duplicates":1068},{"game":"Card 63","wins":5,"duplicates":1219},{"game":"Card 64","wins":1,"duplicates":2430},{"game":"Card 65","wins":1,"duplicates":4860},{"game":"Card 66","wins":1,"duplicates":6206},{"game":"Card 67","wins":3,"duplicates":7426},{"game":"Card 68","wins":0,"duplicates":8646},{"game":"Card 69","wins":1,"duplicates":7427},{"game":"Card 70","wins":1,"duplicates":14854},{"game":"Card 71","wins":0,"duplicates":14855},{"game":"Card 72","wins":9,"duplicates":1},{"game":"Card 73","wins":10,"duplicates":2},{"game":"Card 74","wins":10,"duplicates":4},{"game":"Card 75","wins":10,"duplicates":8},{"game":"Card 76","wins":0,"duplicates":16},{"game":"Card 77","wins":10,"duplicates":16},{"game":"Card 78","wins":0,"duplicates":32},{"game":"Card 79","wins":10,"duplicates":32},{"game":"Card 80","wins":2,"duplicates":64},{"game":"Card 81","wins":5,"duplicates":128},{"game":"Card 82","wins":9,"duplicates":255},{"game":"Card 83","wins":10,"duplicates":446},{"game":"Card 84","wins":1,"duplicates":890},{"game":"Card 85","wins":8,"duplicates":1776},{"game":"Card 86","wins":8,"duplicates":2654},{"game":"Card 87","wins":8,"duplicates":5180},{"game":"Card 88","wins":6,"duplicates":10344},{"game":"Card 89","wins":0,"duplicates":20688},{"game":"Card 90","wins":2,"duplicates":20656},{"game":"Card 91","wins":1,"duplicates":41312},{"game":"Card 92","wins":2,"duplicates":82369},{"game":"Card 93","wins":2,"duplicates":102770},{"game":"Card 94","wins":1,"duplicates":203318},{"game":"Card 95","wins":0,"duplicates":311269},{"game":"Card 96","wins":10,"duplicates":1},{"game":"Card 97","wins":2,"duplicates":2},{"game":"Card 98","wins":5,"duplicates":4},{"game":"Card 99","wins":0,"duplicates":8},{"game":"Card 100","wins":10,"duplicates":6},{"game":"Card 101","wins":3,"duplicates":12},{"game":"Card 102","wins":10,"duplicates":24},{"game":"Card 103","wins":1,"duplicates":48},{"game":"Card 104","wins":4,"duplicates":92},{"game":"Card 105","wins":3,"duplicates":124},{"game":"Card 106","wins":0,"duplicates":248},{"game":"Card 107","wins":1,"duplicates":247},{"game":"Card 108","wins":8,"duplicates":494},{"game":"Card 109","wins":3,"duplicates":525},{"game":"Card 110","wins":3,"duplicates":1050},{"game":"Card 111","wins":4,"duplicates":2094},{"game":"Card 112","wins":3,"duplicates":4188},{"game":"Card 113","wins":0,"duplicates":7827},{"game":"Card 114","wins":1,"duplicates":6777},{"game":"Card 115","wins":0,"duplicates":13554},{"game":"Card 116","wins":0,"duplicates":495},{"game":"Card 117","wins":1,"duplicates":1},{"game":"Card 118","wins":8,"duplicates":2},{"game":"Card 119","wins":6,"duplicates":3},{"game":"Card 120","wins":10,"duplicates":6},{"game":"Card 121","wins":7,"duplicates":12},{"game":"Card 122","wins":7,"duplicates":24},{"game":"Card 123","wins":1,"duplicates":48},{"game":"Card 124","wins":8,"duplicates":96},{"game":"Card 125","wins":5,"duplicates":144},{"game":"Card 126","wins":10,"duplicates":285},{"game":"Card 127","wins":1,"duplicates":568},{"game":"Card 128","wins":0,"duplicates":1136},{"game":"Card 129","wins":1,"duplicates":556},{"game":"Card 130","wins":6,"duplicates":1088},{"game":"Card 131","wins":1,"duplicates":1470},{"game":"Card 132","wins":6,"duplicates":2940},{"game":"Card 133","wins":4,"duplicates":4314},{"game":"Card 134","wins":2,"duplicates":8628},{"game":"Card 135","wins":3,"duplicates":17256},{"game":"Card 136","wins":1,"duplicates":34512},{"game":"Card 137","wins":1,"duplicates":59023},{"game":"Card 138","wins":0,"duplicates":79220},{"game":"Card 139","wins":8,"duplicates":1},{"game":"Card 140","wins":10,"duplicates":2},{"game":"Card 141","wins":8,"duplicates":4},{"game":"Card 142","wins":0,"duplicates":8},{"game":"Card 143","wins":10,"duplicates":8},{"game":"Card 144","wins":10,"duplicates":16},{"game":"Card 145","wins":5,"duplicates":32},{"game":"Card 146","wins":1,"duplicates":64},{"game":"Card 147","wins":10,"duplicates":128},{"game":"Card 148","wins":8,"duplicates":191},{"game":"Card 149","wins":4,"duplicates":382},{"game":"Card 150","wins":7,"duplicates":760},{"game":"Card 151","wins":4,"duplicates":1486},{"game":"Card 152","wins":6,"duplicates":2972},{"game":"Card 153","wins":4,"duplicates":5944},{"game":"Card 154","wins":3,"duplicates":11498},{"game":"Card 155","wins":3,"duplicates":22980},{"game":"Card 156","wins":3,"duplicates":44474},{"game":"Card 157","wins":3,"duplicates":88757},{"game":"Card 158","wins":3,"duplicates":159184},{"game":"Card 159","wins":1,"duplicates":292416},{"game":"Card 160","wins":0,"duplicates":540358},{"game":"Card 161","wins":0,"duplicates":159185},{"game":"Card 162","wins":10,"duplicates":1},{"game":"Card 163","wins":10,"duplicates":2},{"game":"Card 164","wins":6,"duplicates":4},{"game":"Card 165","wins":10,"duplicates":8},{"game":"Card 166","wins":9,"duplicates":16},{"game":"Card 167","wins":10,"duplicates":32},{"game":"Card 168","wins":2,"duplicates":64},{"game":"Card 169","wins":10,"duplicates":128},{"game":"Card 170","wins":10,"duplicates":256},{"game":"Card 171","wins":6,"duplicates":444},{"game":"Card 172","wins":8,"duplicates":888},{"game":"Card 173","wins":6,"duplicates":1775},{"game":"Card 174","wins":8,"duplicates":3548},{"game":"Card 175","wins":7,"duplicates":7096},{"game":"Card 176","wins":2,"duplicates":14168},{"game":"Card 177","wins":0,"duplicates":28336},{"game":"Card 178","wins":7,"duplicates":27860},{"game":"Card 179","wins":0,"duplicates":41552},{"game":"Card 180","wins":0,"duplicates":39649},{"game":"Card 181","wins":3,"duplicates":38505},{"game":"Card 182","wins":1,"duplicates":77010},{"game":"Card 183","wins":2,"duplicates":143376},{"game":"Card 184","wins":1,"duplicates":209742},{"game":"Card 185","wins":0,"duplicates":380979},{"game":"Card 186","wins":0,"duplicates":1},{"game":"Card 187","wins":10,"duplicates":1},{"game":"Card 188","wins":6,"duplicates":2},{"game":"Card 189","wins":10,"duplicates":4},{"game":"Card 190","wins":9,"duplicates":8},{"game":"Card 191","wins":0,"duplicates":16},{"game":"Card 192","wins":10,"duplicates":16},{"game":"Card 193","wins":10,"duplicates":32},{"game":"Card 194","wins":10,"duplicates":64},{"game":"Card 195","wins":8,"duplicates":126},{"game":"Card 196","wins":2,"duplicates":252},{"game":"Card 197","wins":6,"duplicates":504},{"game":"Card 198","wins":3,"duplicates":1007},{"game":"Card 199","wins":1,"duplicates":1762},{"game":"Card 200","wins":2,"duplicates":3512},{"game":"Card 201","wins":0,"duplicates":5262},{"game":"Card 202","wins":4,"duplicates":4255},{"game":"Card 203","wins":0,"duplicates":4982},{"game":"Card 204","wins":2,"duplicates":4320},{"game":"Card 205","wins":1,"duplicates":8576},{"game":"Card 206","wins":0,"duplicates":17152},{"game":"Card 207","wins":0,"duplicates":1},{"game":"Card 208","wins":6,"duplicates":1},{"game":"Card 209","wins":6,"duplicates":2},{"game":"Card 210","wins":4,"duplicates":4},{"game":"Card 211","wins":4,"duplicates":8},{"game":"Card 212","wins":10,"duplicates":16},{"game":"Card 213","wins":1,"duplicates":32},{"game":"Card 214","wins":7,"duplicates":64},{"game":"Card 215","wins":5,"duplicates":91},{"game":"Card 216","wins":2,"duplicates":172},{"game":"Card 217","wins":6,"duplicates":344},{"game":"Card 218","wins":3,"duplicates":688},{"game":"Card 219","wins":3,"duplicates":1204},{"game":"Card 220","wins":1,"duplicates":2408},{"game":"Card 221","wins":0,"duplicates":4725},{"game":"Card 222","wins":1,"duplicates":1565},{"game":"Card 223","wins":0,"duplicates":1910}]